Workbook

Sheet Dashboard
B1: Baltic H₂ Gateway – Klaipėda hydrogen route model
B2: AUVIA Team · Klaipėdos valstybinė kolegija · Portathon 2026, Port of Klaipėda Challenge 1 · Every number updates from the Inputs sheet
B4: Key results
B5: HYDROGEN FOR SALE | D5: USED BY THE TRUCK PLAN | F5: TRUCKS IN THE PLAN | H5: PORT REVENUE | J5: CO₂ AVOIDED | L5: BREAK-EVEN H₂ PRICE
B6: =Capacity!C8/1000 -> 95.25 | D6: =Capacity!C14 -> 0.58464567 | F6: =Capacity!C18 -> 10 | H6: =Capacity!C23/1000 -> 445.5 | J6: =Capacity!C25 -> 590.2875 | L6: =(DieselUse/100*(DieselPrice+CarbonPerLitre/1000*CarbonPrice)+ZevTollSaving)/(HydrogenUse/100) -> 4.8
B8: after the port's own use | D8: =TEXT(Capacity!C13/1000,"0.0")&" t/yr for trucks" -> 55.7 t/yr for trucks | F8: set per route on Routes | H8: ="at €"&TEXT(HydrogenPrice,"0.00")&"/kg" -> at €8.00/kg | J8: diesel the plan replaces | L8: ="vs diesel at €"&TEXT(CarbonPrice,"0")&"/t CO₂" -> vs diesel at €0/t CO₂
B10: Routes at a glance
B11: Route | C11: Lane | F11: Round trip (km/day) | G11: One fill? | H11: Trucks | I11: H₂ per truck (t/yr) | J11: Extra € per round trip | K11: CO₂ saved (t/truck/yr) | L11: H₂ all trucks (t/yr)
B12: =Routes!B6 -> A | C12: =Routes!C6 -> Port-area shuttles | F12: =Routes!H6 -> 180 | G12: =IF(Routes!K6="Yes","Yes","No") -> Yes | H12: =Routes!G6 -> 4 | I12: =Routes!L6/1000 -> 3.375 | J12: =Routes!I16 -> 7.2 | K12: =Routes!K16 -> 35.775 | L12: =Routes!M6/1000 -> 13.5
B13: =Routes!B7 -> B | C13: =Routes!C7 -> Klaipėda ↔ Šiauliai | F13: =Routes!H7 -> 320 | G13: =IF(Routes!K7="Yes","Yes","No") -> Yes | H13: =Routes!G7 -> 3 | I13: =Routes!L7/1000 -> 6 | J13: =Routes!I17 -> 76.8 | K13: =Routes!K17 -> 63.6 | L13: =Routes!M7/1000 -> 18
B14: =Routes!B8 -> C | C14: =Routes!C8 -> Klaipėda ↔ Kaunas | F14: =Routes!H8 -> 430 | G14: =IF(Routes!K8="Yes","Yes","No") -> No | H14: =Routes!G8 -> 3 | I14: =Routes!L8/1000 -> 8.0625 | J14: =Routes!I18 -> 103.2 | K14: =Routes!K18 -> 85.4625 | L14: =Routes!M8/1000 -> 24.1875
B15: =Routes!B9 -> D | C15: =Routes!C9 -> Klaipėda ↔ Vilnius | F15: =Routes!H9 -> 620 | G15: =IF(Routes!K9="Yes","Yes","No") -> No | H15: =Routes!G9 -> 0 | I15: =Routes!L9/1000 -> 11.625 | J15: =Routes!I19 -> 148.8 | K15: =Routes!K19 -> 123.225 | L15: =Routes!M9/1000 -> 0
B16: =Routes!B10 -> E | C16: =Routes!C10 -> Klaipėda ↔ Riga | F16: =Routes!H10 -> 620 | G16: =IF(Routes!K10="Yes","Yes","No") -> No | H16: =Routes!G10 -> 0 | I16: =Routes!L10/1000 -> 11.625 | J16: =Routes!I20 -> 148.8 | K16: =Routes!K20 -> 123.225 | L16: =Routes!M10/1000 -> 0
B17: =Routes!B11 -> F | C17: =Routes!C11 -> Klaipėda ↔ Marijampolė | F17: =Routes!H11 -> 550 | G17: =IF(Routes!K11="Yes","Yes","No") -> No | H17: =Routes!G11 -> 0 | I17: =Routes!L11/1000 -> 10.3125 | J17: =Routes!I21 -> 132 | K17: =Routes!K21 -> 109.3125 | L17: =Routes!M11/1000 -> 0
B18: One fill? No = the round trip needs a second station (Kaunas, Vilnius, Riga or Marijampolė). Trucks in the plan are set on the Routes sheet.
B20: Charts
B38: Chart data (feeds the charts above)
B39: Where the 127 t/yr go | D39: t/yr | F39: Fuel + CO₂ cost per km | I39: €/km
B40: Port's own use | D40: =Capacity!C7/1000 -> 31.75 | F40: ="Diesel at €"&TEXT(CarbonPrice,"0")&"/t CO₂" -> Diesel at €0/t CO₂ | I40: =DieselUse/100*(DieselPrice+CarbonPerLitre/1000*CarbonPrice) -> 0.36
B41: Truck plan | D41: =Capacity!C13/1000 -> 55.6875 | F41: Diesel at €200/t CO₂ | I41: =DieselUse/100*(DieselPrice+CarbonPerLitre/1000*200) -> 0.519
B42: Still unsold | D42: =MAX(0,Capacity!C15/1000) -> 39.5625 | F42: ="H₂ at €"&TEXT(HydrogenPrice,"0.00")&"/kg" -> H₂ at €8.00/kg | I42: =HydrogenUse/100*HydrogenPrice -> 0.6
F43: H₂ at €10.00/kg | I43: =HydrogenUse/100*10 -> 0.75
F44: H₂ at €13.00/kg | I44: =HydrogenUse/100*13 -> 0.975

Sheet Inputs
B1: Inputs
B2: Change the blue numbers. Yellow cells are the levers that matter most for the pitch. Every other sheet updates automatically.
B4: Legend: | C4: Blue text = an input you can change | D4: Key lever | E4: Formula
B6: Group | C6: Input | D6: Value | E6: Unit | F6: Source / note
B7: Plant | C7: Annual hydrogen output at full capacity | D7: 127000 | E7: kg/yr | F7: Port of Klaipėda: 2.25 MW PEM electrolyser (Manifold Times, Jun 2026)
C8: Nameplate daily output | D8: 500 | E8: kg/day | F8: Interreg HyTruck / press (team workshop notes say ~530 kg/day)
C9: Share used by the port authority itself | D9: 0.25 | E9: % | F9: Hydrogen waste-collection vessel + Toyota Mirai: 'about one quarter' (press, Jun 2026)
B10: Prices & carbon | C10: Hydrogen selling price | D10: 8 | E10: €/kg | F10: Pitch assumption: fixed pilot price. Germany truck deal is €8/kg net (hylane + H2 MOBILITY, 2026)
C11: Diesel price, excl. VAT | D11: 1.2 | E11: €/L | F11: Assumption: replace with a current Lithuanian fleet-card price excl. VAT
C12: CO₂ price added to diesel | D12: 0 | E12: €/t CO₂ | F12: 0 = today. EU ETS2 starts 2028 (~€45/t ceiling). Team notes: €70 and €200/t scenarios
C13: CO₂ per litre of diesel burned | D13: 2.65 | E13: kg CO₂/L | F13: Standard tank-to-wheel factor for diesel (~2.64–2.68 kg/L)
B14: Truck & operations | C14: Hydrogen tank (350 bar) | D14: 31.5 | E14: kg | F14: Hyundai XCIENT Fuel Cell, EU spec (ecv.hyundai.com)
C15: Hydrogen use, loaded 40 t truck | D15: 7.5 | E15: kg/100 km | F15: Hyundai quotes ~7 kg/100 km loaded; 7.5 used to stay conservative
C16: Diesel use, loaded 40 t truck | D16: 30 | E16: L/100 km | F16: Assumption: typical EU long-haul 28–33 L/100 km
C17: Safety reserve kept in the tank | D17: 0.15 | E17: % | F17: Assumption: never plan to arrive empty
C18: Working days per year | D18: 250 | E18: days | F18: Assumption
C19: Truck cost premium vs diesel (lease) | D19: 0 | E19: €/truck/yr | F19: NOT INCLUDED until you enter a dealer or lease quote
C20: Toll saving for a zero-emission truck | D20: 0 | E20: €/km | F20: 0 in Lithuania today; Germany gives ~75% off – only matters on German legs

Sheet Routes
B1: Routes
B2: Hydrogen trucks start and end at the Klaipėda station. Blue = route inputs (distance, trips, trucks); yellow = trucks in the plan.
B4: 1 · Operations – can one tank do the job?
B5: Route | C5: Lane | D5: Notes | E5: One-way km | F5: Round trips / day | G5: Trucks in plan | H5: km per day | I5: H₂ per day (kg) | J5: Usable tank (kg) | K5: One fill? | L5: H₂ per truck (kg/yr) | M5: H₂ all trucks (kg/yr)
B6: A | C6: Port-area shuttles | D6: Port ↔ Free Economic Zone, logistics parks and rail terminals | E6: 15 | F6: 6 | G6: 4 | H6: =2*E6*F6 -> 180 | I6: =H6*HydrogenUse/100 -> 13.5 | J6: =TankSize*(1-ReserveShare) -> 26.775 | K6: =IF(I6/F6<=J6,"Yes","No – refuel at far end") -> Yes | L6: =I6*WorkDays -> 3375 | M6: =L6*G6 -> 13500
B7: B | C7: Klaipėda ↔ Šiauliai | D7: Daily shuttle | E7: 160 | F7: 1 | G7: 3 | H7: =2*E7*F7 -> 320 | I7: =H7*HydrogenUse/100 -> 24 | J7: =TankSize*(1-ReserveShare) -> 26.775 | K7: =IF(I7/F7<=J7,"Yes","No – refuel at far end") -> Yes | L7: =I7*WorkDays -> 6000 | M7: =L7*G7 -> 18000
B8: C | C8: Klaipėda ↔ Kaunas | D8: Kaunas Intermodal Terminal; needs a mobile refueller in Kaunas | E8: 215 | F8: 1 | G8: 3 | H8: =2*E8*F8 -> 430 | I8: =H8*HydrogenUse/100 -> 32.25 | J8: =TankSize*(1-ReserveShare) -> 26.775 | K8: =IF(I8/F8<=J8,"Yes","No – refuel at far end") -> No – refuel at far end | L8: =I8*WorkDays -> 8062.5 | M8: =L8*G8 -> 24187.5
B9: D | C9: Klaipėda ↔ Vilnius | D9: Needs a Vilnius station open to trucks | E9: 310 | F9: 1 | G9: 0 | H9: =2*E9*F9 -> 620 | I9: =H9*HydrogenUse/100 -> 46.5 | J9: =TankSize*(1-ReserveShare) -> 26.775 | K9: =IF(I9/F9<=J9,"Yes","No – refuel at far end") -> No – refuel at far end | L9: =I9*WorkDays -> 11625 | M9: =L9*G9 -> 0
B10: E | C10: Klaipėda ↔ Riga | D10: Riga station is not green today | E10: 310 | F10: 1 | G10: 0 | H10: =2*E10*F10 -> 620 | I10: =H10*HydrogenUse/100 -> 46.5 | J10: =TankSize*(1-ReserveShare) -> 26.775 | K10: =IF(I10/F10<=J10,"Yes","No – refuel at far end") -> No – refuel at far end | L10: =I10*WorkDays -> 11625 | M10: =L10*G10 -> 0
B11: F | C11: Klaipėda ↔ Marijampolė | D11: Via Kaunas; refuel at the planned Marijampolė 700-bar station on Via Baltica | E11: 275 | F11: 1 | G11: 0 | H11: =2*E11*F11 -> 550 | I11: =H11*HydrogenUse/100 -> 41.25 | J11: =TankSize*(1-ReserveShare) -> 26.775 | K11: =IF(I11/F11<=J11,"Yes","No – refuel at far end") -> No – refuel at far end | L11: =I11*WorkDays -> 10312.5 | M11: =L11*G11 -> 0
B12: Total for the plan | G12: =SUM(G6:G11) -> 10 | M12: =SUM(M6:M11) -> 55687.5
B14: 2 · Economics & climate – one truck compared with diesel
B15: Route | C15: Lane | E15: Diesel fuel (€/km) | F15: CO₂ cost on diesel (€/km) | G15: H₂ fuel (€/km) | H15: Extra cost vs diesel (€/km) | I15: Extra cost per round trip (€) | J15: Extra cost per truck (€/yr) | K15: CO₂ saved per truck (t/yr) | L15: Cost per t CO₂ avoided (€/t)
B16: =B6 -> A | C16: =C6 -> Port-area shuttles | E16: =DieselUse/100*DieselPrice -> 0.36 | F16: =DieselUse/100*CarbonPerLitre/1000*CarbonPrice -> 0 | G16: =HydrogenUse/100*HydrogenPrice -> 0.6 | H16: =G16-E16-F16-ZevTollSaving -> 0.24 | I16: =H16*2*E6 -> 7.2 | J16: =H16*H6*WorkDays+TruckPremium -> 10800 | K16: =H6*WorkDays*DieselUse/100*CarbonPerLitre/1000 -> 35.775 | L16: =IF(K16>0,J16/K16,0) -> 301.88679
B17: =B7 -> B | C17: =C7 -> Klaipėda ↔ Šiauliai | E17: =DieselUse/100*DieselPrice -> 0.36 | F17: =DieselUse/100*CarbonPerLitre/1000*CarbonPrice -> 0 | G17: =HydrogenUse/100*HydrogenPrice -> 0.6 | H17: =G17-E17-F17-ZevTollSaving -> 0.24 | I17: =H17*2*E7 -> 76.8 | J17: =H17*H7*WorkDays+TruckPremium -> 19200 | K17: =H7*WorkDays*DieselUse/100*CarbonPerLitre/1000 -> 63.6 | L17: =IF(K17>0,J17/K17,0) -> 301.88679
B18: =B8 -> C | C18: =C8 -> Klaipėda ↔ Kaunas | E18: =DieselUse/100*DieselPrice -> 0.36 | F18: =DieselUse/100*CarbonPerLitre/1000*CarbonPrice -> 0 | G18: =HydrogenUse/100*HydrogenPrice -> 0.6 | H18: =G18-E18-F18-ZevTollSaving -> 0.24 | I18: =H18*2*E8 -> 103.2 | J18: =H18*H8*WorkDays+TruckPremium -> 25800 | K18: =H8*WorkDays*DieselUse/100*CarbonPerLitre/1000 -> 85.4625 | L18: =IF(K18>0,J18/K18,0) -> 301.88679
B19: =B9 -> D | C19: =C9 -> Klaipėda ↔ Vilnius | E19: =DieselUse/100*DieselPrice -> 0.36 | F19: =DieselUse/100*CarbonPerLitre/1000*CarbonPrice -> 0 | G19: =HydrogenUse/100*HydrogenPrice -> 0.6 | H19: =G19-E19-F19-ZevTollSaving -> 0.24 | I19: =H19*2*E9 -> 148.8 | J19: =H19*H9*WorkDays+TruckPremium -> 37200 | K19: =H9*WorkDays*DieselUse/100*CarbonPerLitre/1000 -> 123.225 | L19: =IF(K19>0,J19/K19,0) -> 301.88679
B20: =B10 -> E | C20: =C10 -> Klaipėda ↔ Riga | E20: =DieselUse/100*DieselPrice -> 0.36 | F20: =DieselUse/100*CarbonPerLitre/1000*CarbonPrice -> 0 | G20: =HydrogenUse/100*HydrogenPrice -> 0.6 | H20: =G20-E20-F20-ZevTollSaving -> 0.24 | I20: =H20*2*E10 -> 148.8 | J20: =H20*H10*WorkDays+TruckPremium -> 37200 | K20: =H10*WorkDays*DieselUse/100*CarbonPerLitre/1000 -> 123.225 | L20: =IF(K20>0,J20/K20,0) -> 301.88679
B21: =B11 -> F | C21: =C11 -> Klaipėda ↔ Marijampolė | E21: =DieselUse/100*DieselPrice -> 0.36 | F21: =DieselUse/100*CarbonPerLitre/1000*CarbonPrice -> 0 | G21: =HydrogenUse/100*HydrogenPrice -> 0.6 | H21: =G21-E21-F21-ZevTollSaving -> 0.24 | I21: =H21*2*E11 -> 132 | J21: =H21*H11*WorkDays+TruckPremium -> 33000 | K21: =H11*WorkDays*DieselUse/100*CarbonPerLitre/1000 -> 109.3125 | L21: =IF(K21>0,J21/K21,0) -> 301.88679
B23: Notes
B24: • Distances are approximate road km – check them on a map before quoting.
B25: • Route A: 6 short round trips a day (~180 km) moving containers between the port and nearby sites.
B26: • 'One fill?' checks one round trip against the tank minus the safety reserve. Routes C–F need a refuel at the far end.
B27: • Route F becomes possible once the Marijampolė station opens (Baltic H₂ Gateway stage 3, 2028+); it links Lithuania to Poland on Via Baltica.
B28: • Extra cost per truck includes the truck lease premium from Inputs (0 until you add a quote). CO₂ saved is tank-to-wheel.

Sheet Capacity
B1: Capacity
B2: Does the truck plan fit the plant? Supply, demand and value. Change trucks per route on the Routes sheet.
B4: Supply
B5: Item | C5: Value | D5: Unit | E5: How it's calculated
B6: Plant output at full capacity | C6: =PlantOutput -> 127000 | D6: kg/yr | E6: From Inputs
B7: Used by the port authority itself | C7: =PlantOutput*PortOwnShare -> 31750 | D7: kg/yr | E7: Output × port's own share
B8: Available to sell | C8: =C6-C7 -> 95250 | D8: kg/yr | E8: Output minus the port's own use
B9: Available to sell per working day | C9: =C8/WorkDays -> 381 | D9: kg/day | E9: Spread over the working days
B11: Demand from the truck plan
B12: Item | C12: Value | D12: Unit | E12: How it's calculated
B13: Hydrogen needed by all trucks in the plan | C13: =Routes!M12 -> 55687.5 | D13: kg/yr | E13: Routes sheet, total of table 1
B14: Share of sellable hydrogen used | C14: =IF(C8>0,C13/C8,0) -> 0.58464567 | D14: % | E14: Plan ÷ available to sell
B15: Hydrogen still unsold | C15: =C8-C13 -> 39562.5 | D15: kg/yr | E15: Room to add trucks or industrial buyers
B16: Plan demand on a working day | C16: =SUMPRODUCT(Routes!I6:I11,Routes!G6:G11) -> 222.75 | D16: kg/day | E16: Daily fills across all routes
B17: Peak day fits the nameplate daily output? | C17: =IF(C16+C7/WorkDays<=DailyCapacity,"Yes","No – add storage or stagger fills") -> Yes | E17: Plan + port's own daily use vs nameplate
B18: Trucks in the plan | C18: =Routes!G12 -> 10 | D18: trucks | E18: Routes sheet
B19: Route B trucks the sellable hydrogen could support | C19: =IF(Routes!L7>0,C8/Routes!L7,0) -> 15.875 | D19: trucks | E19: Available ÷ one Šiauliai truck's yearly need
B21: Value
B22: Item | C22: Value | D22: Unit | E22: How it's calculated
B23: Port revenue from the plan at the selected price | C23: =C13*HydrogenPrice -> 445500 | D23: €/yr | E23: Plan × hydrogen price
B24: Port revenue if all sellable hydrogen is sold | C24: =C8*HydrogenPrice -> 762000 | D24: €/yr | E24: Available × hydrogen price
B25: CO₂ avoided by the plan | C25: =SUMPRODUCT(Routes!K16:K21,Routes!G6:G11) -> 590.2875 | D25: t/yr | E25: Diesel CO₂ the plan replaces
B26: Pilot volume to ask for (Routes A + B) | C26: =Routes!M6+Routes!M7 -> 31500 | D26: kg/yr | E26: Deck ask: fixed price for a 12-month pilot

Sheet Bridge Sale
B1: Bridge Sale
B2: Deck stage 1: a 1.5 t trial batch to industry, delivered by 350-bar tube trailer. No new vehicles needed.
B4: Trial batch
B5: Item | C5: Value | D5: Unit | E5: Note
B6: Trial batch size | C6: 1500 | D6: kg | E6: Deck stage 1: 1.5 t
B7: Price – low case | C7: 8 | D7: €/kg | E7: Benchmark: €8/kg truck hydrogen in Germany (2026)
B8: Price – high case | C8: 12 | D8: €/kg | E8: Upper benchmark
B9: Revenue – low case | C9: =C6*C7 -> 12000 | D9: € | E9: Batch × low price
B10: Revenue – high case | C10: =C6*C8 -> 18000 | D10: € | E10: Batch × high price
B11: Share of the hydrogen for sale | C11: =C6/Capacity!C8 -> 0.015748031 | D11: % | E11: Trial vs a year of sellable output
B12: Days of spare output used | C12: =C6/Capacity!C9 -> 3.9370079 | D12: working days | E12: How long the plant needs to make the batch
B14: Candidate buyers
B15: Buyer | C15: Site | D15: Road km from Klaipėda | E15: Use of hydrogen
B16: Orlen Lietuva | C16: Mažeikiai refinery | D16: 150 | E16: Hydrotreating – removing sulphur from diesel and petrol
B17: Achema | C17: Jonava fertiliser plant | D17: 245 | E17: Feedstock for ammonia (NH₃) – replacing grey hydrogen
B19: Distances are approximate road km. Final price depends on buyer terms, purity and delivery.

Sheet Sensitivity
B1: Sensitivity
B2: Extra fuel cost of a hydrogen truck vs diesel, € per km, for each hydrogen price and CO₂ price. Green = hydrogen is cheaper.
B4: Hydrogen price × CO₂ price
B5: H₂ price ↓ CO₂ price → | C5: 0 | D5: 45 | E5: 70 | F5: 100 | G5: 200 | I5: How to read it
B6: 5 | C6: =$B6*HydrogenUse/100-DieselUse/100*(DieselPrice+CarbonPerLitre/1000*C$5)-ZevTollSaving -> 0.015 | D6: =$B6*HydrogenUse/100-DieselUse/100*(DieselPrice+CarbonPerLitre/1000*D$5)-ZevTollSaving -> -0.020775 | E6: =$B6*HydrogenUse/100-DieselUse/100*(DieselPrice+CarbonPerLitre/1000*E$5)-ZevTollSaving -> -0.04065 | F6: =$B6*HydrogenUse/100-DieselUse/100*(DieselPrice+CarbonPerLitre/1000*F$5)-ZevTollSaving -> -0.0645 | G6: =$B6*HydrogenUse/100-DieselUse/100*(DieselPrice+CarbonPerLitre/1000*G$5)-ZevTollSaving -> -0.144 | I6: Each cell = hydrogen fuel cost per km minus diesel fuel + CO₂ cost per km.
B7: 6 | C7: =$B7*HydrogenUse/100-DieselUse/100*(DieselPrice+CarbonPerLitre/1000*C$5)-ZevTollSaving -> 0.09 | D7: =$B7*HydrogenUse/100-DieselUse/100*(DieselPrice+CarbonPerLitre/1000*D$5)-ZevTollSaving -> 0.054225 | E7: =$B7*HydrogenUse/100-DieselUse/100*(DieselPrice+CarbonPerLitre/1000*E$5)-ZevTollSaving -> 0.03435 | F7: =$B7*HydrogenUse/100-DieselUse/100*(DieselPrice+CarbonPerLitre/1000*F$5)-ZevTollSaving -> 0.0105 | G7: =$B7*HydrogenUse/100-DieselUse/100*(DieselPrice+CarbonPerLitre/1000*G$5)-ZevTollSaving -> -0.069 | I7: Green: hydrogen is already cheaper. Red: hydrogen costs more.
B8: 7 | C8: =$B8*HydrogenUse/100-DieselUse/100*(DieselPrice+CarbonPerLitre/1000*C$5)-ZevTollSaving -> 0.165 | D8: =$B8*HydrogenUse/100-DieselUse/100*(DieselPrice+CarbonPerLitre/1000*D$5)-ZevTollSaving -> 0.129225 | E8: =$B8*HydrogenUse/100-DieselUse/100*(DieselPrice+CarbonPerLitre/1000*E$5)-ZevTollSaving -> 0.10935 | F8: =$B8*HydrogenUse/100-DieselUse/100*(DieselPrice+CarbonPerLitre/1000*F$5)-ZevTollSaving -> 0.0855 | G8: =$B8*HydrogenUse/100-DieselUse/100*(DieselPrice+CarbonPerLitre/1000*G$5)-ZevTollSaving -> 0.006 | I8: The yellow row is the hydrogen price where both cost the same.
B9: 8 | C9: =$B9*HydrogenUse/100-DieselUse/100*(DieselPrice+CarbonPerLitre/1000*C$5)-ZevTollSaving -> 0.24 | D9: =$B9*HydrogenUse/100-DieselUse/100*(DieselPrice+CarbonPerLitre/1000*D$5)-ZevTollSaving -> 0.204225 | E9: =$B9*HydrogenUse/100-DieselUse/100*(DieselPrice+CarbonPerLitre/1000*E$5)-ZevTollSaving -> 0.18435 | F9: =$B9*HydrogenUse/100-DieselUse/100*(DieselPrice+CarbonPerLitre/1000*F$5)-ZevTollSaving -> 0.1605 | G9: =$B9*HydrogenUse/100-DieselUse/100*(DieselPrice+CarbonPerLitre/1000*G$5)-ZevTollSaving -> 0.081
B10: 9 | C10: =$B10*HydrogenUse/100-DieselUse/100*(DieselPrice+CarbonPerLitre/1000*C$5)-ZevTollSaving -> 0.315 | D10: =$B10*HydrogenUse/100-DieselUse/100*(DieselPrice+CarbonPerLitre/1000*D$5)-ZevTollSaving -> 0.279225 | E10: =$B10*HydrogenUse/100-DieselUse/100*(DieselPrice+CarbonPerLitre/1000*E$5)-ZevTollSaving -> 0.25935 | F10: =$B10*HydrogenUse/100-DieselUse/100*(DieselPrice+CarbonPerLitre/1000*F$5)-ZevTollSaving -> 0.2355 | G10: =$B10*HydrogenUse/100-DieselUse/100*(DieselPrice+CarbonPerLitre/1000*G$5)-ZevTollSaving -> 0.156 | I10: CO₂ columns
B11: 10 | C11: =$B11*HydrogenUse/100-DieselUse/100*(DieselPrice+CarbonPerLitre/1000*C$5)-ZevTollSaving -> 0.39 | D11: =$B11*HydrogenUse/100-DieselUse/100*(DieselPrice+CarbonPerLitre/1000*D$5)-ZevTollSaving -> 0.354225 | E11: =$B11*HydrogenUse/100-DieselUse/100*(DieselPrice+CarbonPerLitre/1000*E$5)-ZevTollSaving -> 0.33435 | F11: =$B11*HydrogenUse/100-DieselUse/100*(DieselPrice+CarbonPerLitre/1000*F$5)-ZevTollSaving -> 0.3105 | G11: =$B11*HydrogenUse/100-DieselUse/100*(DieselPrice+CarbonPerLitre/1000*G$5)-ZevTollSaving -> 0.231 | I11: €0 = today · €45 = EU ETS2 ceiling from 2028
B12: 11 | C12: =$B12*HydrogenUse/100-DieselUse/100*(DieselPrice+CarbonPerLitre/1000*C$5)-ZevTollSaving -> 0.465 | D12: =$B12*HydrogenUse/100-DieselUse/100*(DieselPrice+CarbonPerLitre/1000*D$5)-ZevTollSaving -> 0.429225 | E12: =$B12*HydrogenUse/100-DieselUse/100*(DieselPrice+CarbonPerLitre/1000*E$5)-ZevTollSaving -> 0.40935 | F12: =$B12*HydrogenUse/100-DieselUse/100*(DieselPrice+CarbonPerLitre/1000*F$5)-ZevTollSaving -> 0.3855 | G12: =$B12*HydrogenUse/100-DieselUse/100*(DieselPrice+CarbonPerLitre/1000*G$5)-ZevTollSaving -> 0.306 | I12: €70 and €200 = team workshop scenarios · €100 = midpoint
B13: 12 | C13: =$B13*HydrogenUse/100-DieselUse/100*(DieselPrice+CarbonPerLitre/1000*C$5)-ZevTollSaving -> 0.54 | D13: =$B13*HydrogenUse/100-DieselUse/100*(DieselPrice+CarbonPerLitre/1000*D$5)-ZevTollSaving -> 0.504225 | E13: =$B13*HydrogenUse/100-DieselUse/100*(DieselPrice+CarbonPerLitre/1000*E$5)-ZevTollSaving -> 0.48435 | F13: =$B13*HydrogenUse/100-DieselUse/100*(DieselPrice+CarbonPerLitre/1000*F$5)-ZevTollSaving -> 0.4605 | G13: =$B13*HydrogenUse/100-DieselUse/100*(DieselPrice+CarbonPerLitre/1000*G$5)-ZevTollSaving -> 0.381
B14: 13 | C14: =$B14*HydrogenUse/100-DieselUse/100*(DieselPrice+CarbonPerLitre/1000*C$5)-ZevTollSaving -> 0.615 | D14: =$B14*HydrogenUse/100-DieselUse/100*(DieselPrice+CarbonPerLitre/1000*D$5)-ZevTollSaving -> 0.579225 | E14: =$B14*HydrogenUse/100-DieselUse/100*(DieselPrice+CarbonPerLitre/1000*E$5)-ZevTollSaving -> 0.55935 | F14: =$B14*HydrogenUse/100-DieselUse/100*(DieselPrice+CarbonPerLitre/1000*F$5)-ZevTollSaving -> 0.5355 | G14: =$B14*HydrogenUse/100-DieselUse/100*(DieselPrice+CarbonPerLitre/1000*G$5)-ZevTollSaving -> 0.456 | I14: Not included
B15: 14 | C15: =$B15*HydrogenUse/100-DieselUse/100*(DieselPrice+CarbonPerLitre/1000*C$5)-ZevTollSaving -> 0.69 | D15: =$B15*HydrogenUse/100-DieselUse/100*(DieselPrice+CarbonPerLitre/1000*D$5)-ZevTollSaving -> 0.654225 | E15: =$B15*HydrogenUse/100-DieselUse/100*(DieselPrice+CarbonPerLitre/1000*E$5)-ZevTollSaving -> 0.63435 | F15: =$B15*HydrogenUse/100-DieselUse/100*(DieselPrice+CarbonPerLitre/1000*F$5)-ZevTollSaving -> 0.6105 | G15: =$B15*HydrogenUse/100-DieselUse/100*(DieselPrice+CarbonPerLitre/1000*G$5)-ZevTollSaving -> 0.531 | I15: Truck lease premium (see Inputs) and toll savings outside Germany.
B17: Break-even H₂ price (€/kg) | C17: =(DieselUse/100*(DieselPrice+CarbonPerLitre/1000*C$5)+ZevTollSaving)/(HydrogenUse/100) -> 4.8 | D17: =(DieselUse/100*(DieselPrice+CarbonPerLitre/1000*D$5)+ZevTollSaving)/(HydrogenUse/100) -> 5.277 | E17: =(DieselUse/100*(DieselPrice+CarbonPerLitre/1000*E$5)+ZevTollSaving)/(HydrogenUse/100) -> 5.542 | F17: =(DieselUse/100*(DieselPrice+CarbonPerLitre/1000*F$5)+ZevTollSaving)/(HydrogenUse/100) -> 5.86 | G17: =(DieselUse/100*(DieselPrice+CarbonPerLitre/1000*G$5)+ZevTollSaving)/(HydrogenUse/100) -> 6.92

Sheet Guide & Sources
B1: Guide & Sources
B2: What this workbook does, how to use it, and where every number comes from.
B4: What it does
B5: Compares hydrogen truck routes that start and end at the Port of Klaipėda hydrogen station, checks the plan against the 127 t/yr the plant can make, and prices the 1.5 t industrial bridge sale.
B7: Sheets
B8: Dashboard | C8: Key results, routes at a glance and two charts – start here
B9: Inputs | C9: Every assumption with its source; change the blue numbers
B10: Routes | C10: Per-truck operations (range, fills) and economics vs diesel for routes A–F
B11: Capacity | C11: Supply vs demand, revenue and CO₂ for the whole plan
B12: Bridge Sale | C12: The 1.5 t trial batch to Orlen Lietuva or Achema
B13: Sensitivity | C13: Hydrogen price × CO₂ price grid and break-even prices
B15: Colour code
B16: 1,234 | C16: Blue text – an input you can change
B17: 1,234 | C17: Black text – a formula on the same sheet
B18: 1,234 | C18: Green text – pulled from another sheet
B19: 1,234 | C19: Yellow fill – a key lever for the pitch
B20: Yes | C20: Green / amber – a route fits one fill, or needs a second station
B22: How to use it
B23: 1. Change the yellow cells on Inputs: hydrogen price, diesel price, CO₂ price, truck lease premium.
B24: 2. Set trucks per route on Routes (yellow column).
B25: 3. Read the Dashboard. Every other cell is a formula – please don't overwrite them.
B27: Not in the numbers yet
B28: • The extra purchase or lease cost of a fuel-cell truck is 0 until you enter a real quote (Inputs).
B29: • Toll savings are 0: Lithuania gives zero-emission trucks no discount today (a CO₂-based distance toll is coming).
B30: • Road distances are approximate – check them on a map before quoting.
B32: Sources
B33: • Plant 127 t/yr, 2.25 MW PEM, ~500 kg/day, 350 & 700 bar, ~¼ for the port's own use: Port of Klaipėda / Manifold Times (Jun 2026), Ship & Bunker, Interreg HyTruck
B34: • Truck tank 31.5 kg at 350 bar, ~400 km, ~7 kg/100 km loaded: Hyundai XCIENT Fuel Cell, EU spec (ecv.hyundai.com)
B35: • EU ETS2 for road fuels from 2028, price ceiling mechanism near €45/t: climate.ec.europa.eu
... B40: AUVIA Team – Mahyi Eddine Bouaffar, Chukwuemeka Onyemejor, Mokhtar Ounis, Salah Djoudi, Lotfi Boumaza · Mentor: Lina Gelažnikienė · Klaipėdos valstybinė kolegija
